<?xml version='1.0' encoding='UTF-8' standalone='yes' ?><hierarchy index="0" class="hierarchy" rotation="0" width="1080" height="1977">  <android.widget.FrameLayout index="0" package="com.chewy.android" class="android.widget.FrameLayout" text="" checkable="false" checked="false" clickable="false" enabled="true" focusable="false" focused="false" long-clickable="false" password="false" scrollable="false" selected="false" bounds="[0,0][1080,1977]" displayed="true">    <android.widget.LinearLayout index="0" package="com.chewy.android" class="android.widget.LinearLayout" text="" checkable="false" checked="false" clickable="false" enabled="true" focusable="false" focused="false" long-clickable="false" password="false" scrollable="false" selected="false" bounds="[0,0][1080,1977]" displayed="true">      <android.widget.FrameLayout index="0" package="com.chewy.android" class="android.widget.FrameLayout" text="" checkable="false" checked="false" clickable="false" enabled="true" focusable="false" focused="false" long-clickable="false" password="false" scrollable="false" selected="false" bounds="[0,0][1080,1977]" displayed="true">        <android.widget.LinearLayout index="0" package="com.chewy.android" class="android.widget.LinearLayout" text="" resource-id="com.chewy.android:id/action_bar_root" checkable="false" checked="false" clickable="false" enabled="true" focusable="false" focused="false" long-clickable="false" password="false" scrollable="false" selected="false" bounds="[0,0][1080,1977]" displayed="true">          <android.widget.FrameLayout index="0" package="com.chewy.android" class="android.widget.FrameLayout" text="" resource-id="android:id/content" checkable="false" checked="false" clickable="false" enabled="true" focusable="false" focused="false" long-clickable="false" password="false" scrollable="false" selected="false" bounds="[0,0][1080,1977]" displayed="true">            <androidx.drawerlayout.widget.DrawerLayout index="0" package="com.chewy.android" class="androidx.drawerlayout.widget.DrawerLayout" text="" resource-id="com.chewy.android:id/drawerLayoutShop" checkable="false" checked="false" clickable="false" enabled="true" focusable="false" focused="false" long-clickable="false" password="false" scrollable="false" selected="false" bounds="[0,0][1080,1977]" displayed="true">              <android.view.ViewGroup index="0" package="com.chewy.android" class="android.view.ViewGroup" text="" checkable="false" checked="false" clickable="false" enabled="true" focusable="false" focused="false" long-clickable="false" password="false" scrollable="false" selected="false" bounds="[0,171][1080,1977]" displayed="true">                <android.view.ViewGroup index="0" package="com.chewy.android" class="android.view.ViewGroup" text="" checkable="false" checked="false" clickable="false" enabled="true" focusable="false" focused="false" long-clickable="false" password="false" scrollable="false" selected="false" bounds="[0,171][1080,1977]" displayed="true">                  <android.widget.LinearLayout index="0" package="com.chewy.android" class="android.widget.LinearLayout" text="" resource-id="com.chewy.android:id/appBarShop" checkable="false" checked="false" clickable="false" enabled="true" focusable="false" focused="false" long-clickable="false" password="false" scrollable="false" selected="false" bounds="[0,171][1080,529]" displayed="true">                    <android.widget.FrameLayout index="0" package="com.chewy.android" class="android.widget.FrameLayout" text="" checkable="false" checked="false" clickable="false" enabled="true" focusable="false" focused="false" long-clickable="false" password="false" scrollable="false" selected="false" bounds="[0,171][1080,529]" displayed="true">                      <android.widget.LinearLayout index="0" package="com.chewy.android" class="android.widget.LinearLayout" text="" checkable="false" checked="false" clickable="false" enabled="true" focusable="false" focused="false" long-clickable="false" password="false" scrollable="false" selected="false" bounds="[0,171][1080,529]" displayed="true">                        <android.view.ViewGroup index="0" package="com.chewy.android" class="android.view.ViewGroup" text="" resource-id="com.chewy.android:id/toolbarShop" checkable="false" checked="false" clickable="false" enabled="true" focusable="false" focused="false" long-clickable="false" password="false" scrollable="false" selected="false" bounds="[0,171][1080,325]" displayed="true">                          <android.widget.ImageButton index="0" package="com.chewy.android" class="android.widget.ImageButton" text="" content-desc="Open navigation drawer" checkable="false" checked="false" clickable="true" enabled="true" focusable="true" focused="false" long-clickable="false" password="false" scrollable="false" selected="false" bounds="[0,171][154,325]" displayed="true" />                          <android.widget.TextView index="1" package="com.chewy.android" class="android.widget.TextView" text="Shop" checkable="false" checked="false" clickable="false" enabled="true" focusable="false" focused="false" long-clickable="false" password="false" scrollable="false" selected="false" bounds="[198,211][328,285]" displayed="true" />                          <androidx.appcompat.widget.g0 index="2" package="com.chewy.android" class="androidx.appcompat.widget.g0" text="" checkable="false" checked="false" clickable="false" enabled="true" focusable="false" focused="false" long-clickable="false" password="false" scrollable="false" selected="false" bounds="[816,171][1080,325]" displayed="true">                            <android.widget.TextView index="0" package="com.chewy.android" class="android.widget.TextView" text="" content-desc="Search" resource-id="com.chewy.android:id/action_search" checkable="false" checked="false" clickable="true" enabled="true" focusable="true" focused="false" long-clickable="false" password="false" scrollable="false" selected="false" bounds="[816,182][948,314]" displayed="true" />                            <android.widget.TextView index="1" package="com.chewy.android" class="android.widget.TextView" text="" content-desc="0 items in shopping cart" resource-id="com.chewy.android:id/action_shopping_cart" checkable="false" checked="false" clickable="true" enabled="true" focusable="true" focused="false" long-clickable="false" password="false" scrollable="false" selected="false" bounds="[948,182][1080,314]" displayed="true" />                          </androidx.appcompat.widget.g0>                        </android.view.ViewGroup>                        <android.widget.HorizontalScrollView index="1" package="com.chewy.android" class="android.widget.HorizontalScrollView" text="" resource-id="com.chewy.android:id/tabLayoutShop" checkable="false" checked="false" clickable="false" enabled="true" focusable="true" focused="false" long-clickable="false" password="false" scrollable="true" selected="false" bounds="[0,325][981,479]" displayed="true">                          <android.widget.LinearLayout index="0" package="com.chewy.android" class="android.widget.LinearLayout" text="" checkable="false" checked="false" clickable="false" enabled="true" focusable="false" focused="false" long-clickable="false" password="false" scrollable="false" selected="false" bounds="[0,325][981,479]" displayed="true">                            <androidx.appcompat.app.a.c index="0" package="com.chewy.android" class="androidx.appcompat.app.a$c" text="" checkable="false" checked="false" clickable="true" enabled="true" focusable="true" focused="false" long-clickable="false" password="false" scrollable="false" selected="false" bounds="[0,325][125,479]" displayed="true">                              <android.view.ViewGroup index="0" package="com.chewy.android" class="android.view.ViewGroup" text="" checkable="false" checked="false" clickable="false" enabled="true" focusable="false" focused="false" long-clickable="false" password="false" scrollable="false" selected="false" bounds="[0,325][125,479]" displayed="true">                                <android.widget.TextView index="0" package="com.chewy.android" class="android.widget.TextView" text="Cat" resource-id="com.chewy.android:id/tabText" checkable="false" checked="false" clickable="false" enabled="true" focusable="false" focused="false" long-clickable="false" password="false" scrollable="false" selected="false" bounds="[36,373][103,432]" displayed="true" />                              </android.view.ViewGroup>                            </androidx.appcompat.app.a.c>                            <androidx.appcompat.app.a.c index="1" package="com.chewy.android" class="androidx.appcompat.app.a$c" text="" checkable="false" checked="false" clickable="true" enabled="true" focusable="true" focused="false" long-clickable="false" password="false" scrollable="false" selected="false" bounds="[125,325][326,479]" displayed="true">                              <android.view.ViewGroup index="0" package="com.chewy.android" class="android.view.ViewGroup" text="" checkable="false" checked="false" clickable="false" enabled="true" focusable="false" focused="false" long-clickable="false" password="false" scrollable="false" selected="false" bounds="[125,325][326,479]" displayed="true">                                <android.widget.ImageView index="0" package="com.chewy.android" class="android.widget.ImageView" text="" resource-id="com.chewy.android:id/dividerCarrot" checkable="false" checked="false" clickable="false" enabled="true" focusable="false" focused="false" long-clickable="false" password="false" scrollable="false" selected="false" bounds="[147,384][161,420]" displayed="true" />                                <android.widget.TextView index="1" package="com.chewy.android" class="android.widget.TextView" text="Food" resource-id="com.chewy.android:id/tabText" checkable="false" checked="false" clickable="false" enabled="true" focusable="false" focused="false" long-clickable="false" password="false" scrollable="false" selected="false" bounds="[205,373][304,432]" displayed="true" />                              </android.view.ViewGroup>                            </androidx.appcompat.app.a.c>                            <androidx.appcompat.app.a.c index="2" package="com.chewy.android" class="androidx.appcompat.app.a$c" text="" checkable="false" checked="false" clickable="true" enabled="true" focusable="true" focused="false" long-clickable="false" password="false" scrollable="false" selected="false" bounds="[326,325][613,479]" displayed="true">                              <android.view.ViewGroup index="0" package="com.chewy.android" class="android.view.ViewGroup" text="" checkable="false" checked="false" clickable="false" enabled="true" focusable="false" focused="false" long-clickable="false" password="false" scrollable="false" selected="false" bounds="[326,325][613,479]" displayed="true">                                <android.widget.ImageView index="0" package="com.chewy.android" class="android.widget.ImageView" text="" resource-id="com.chewy.android:id/dividerCarrot" checkable="false" checked="false" clickable="false" enabled="true" focusable="false" focused="false" long-clickable="false" password="false" scrollable="false" selected="false" bounds="[348,384][362,420]" displayed="true" />                                <android.widget.TextView index="1" package="com.chewy.android" class="android.widget.TextView" text="Wet Food" resource-id="com.chewy.android:id/tabText" checkable="false" checked="false" clickable="false" enabled="true" focusable="false" focused="false" long-clickable="false" password="false" scrollable="false" selected="false" bounds="[406,373][591,432]" displayed="true" />                              </android.view.ViewGroup>                            </androidx.appcompat.app.a.c>                            <androidx.appcompat.app.a.c index="3" package="com.chewy.android" class="androidx.appcompat.app.a$c" text="" checkable="false" checked="false" clickable="true" enabled="true" focusable="true" focused="false" long-clickable="false" password="false" scrollable="false" selected="true" bounds="[613,325][981,479]" displayed="true">                              <android.view.ViewGroup index="0" package="com.chewy.android" class="android.view.ViewGroup" text="" checkable="false" checked="false" clickable="false" enabled="true" focusable="false" focused="false" long-clickable="false" password="false" scrollable="false" selected="true" bounds="[613,325][981,479]" displayed="true">                                <android.widget.ImageView index="0" package="com.chewy.android" class="android.widget.ImageView" text="" resource-id="com.chewy.android:id/dividerCarrot" checkable="false" checked="false" clickable="false" enabled="true" focusable="false" focused="false" long-clickable="false" password="false" scrollable="false" selected="true" bounds="[635,384][649,420]" displayed="true" />                                <android.widget.TextView index="1" package="com.chewy.android" class="android.widget.TextView" text="Variety Packs" resource-id="com.chewy.android:id/tabText" checkable="false" checked="false" clickable="false" enabled="true" focusable="false" focused="false" long-clickable="false" password="false" scrollable="false" selected="true" bounds="[693,373][959,432]" displayed="true" />                              </android.view.ViewGroup>                            </androidx.appcompat.app.a.c>                          </android.widget.LinearLayout>                        </android.widget.HorizontalScrollView>                      </android.widget.LinearLayout>                      <android.widget.FrameLayout index="1" package="com.chewy.android" class="android.widget.FrameLayout" text="" checkable="false" checked="false" clickable="false" enabled="true" focusable="false" focused="false" long-clickable="false" password="false" scrollable="false" selected="false" bounds="[0,518][1080,529]" displayed="true" />                    </android.widget.FrameLayout>                  </android.widget.LinearLayout>                  <android.widget.FrameLayout index="1" package="com.chewy.android" class="android.widget.FrameLayout" text="" resource-id="com.chewy.android:id/content_shop" checkable="false" checked="false" clickable="false" enabled="true" focusable="false" focused="false" long-clickable="false" password="false" scrollable="false" selected="false" bounds="[0,529][1080,1977]" displayed="true">                    <android.view.ViewGroup index="0" package="com.chewy.android" class="android.view.ViewGroup" text="" resource-id="com.chewy.android:id/browseResultSwipeRefresh" checkable="false" checked="false" clickable="false" enabled="true" focusable="false" focused="false" long-clickable="false" password="false" scrollable="false" selected="false" bounds="[0,529][1080,1977]" displayed="true">                      <android.view.ViewGroup index="0" package="com.chewy.android" class="android.view.ViewGroup" text="" checkable="false" checked="false" clickable="false" enabled="true" focusable="false" focused="false" long-clickable="false" password="false" scrollable="false" selected="false" bounds="[0,529][1080,1977]" displayed="true">                        <androidx.recyclerview.widget.RecyclerView index="0" package="com.chewy.android" class="androidx.recyclerview.widget.RecyclerView" text="" resource-id="com.chewy.android:id/browseResultsList" checkable="false" checked="false" clickable="false" enabled="true" focusable="true" focused="false" long-clickable="false" password="false" scrollable="true" selected="false" bounds="[0,529][1080,1977]" displayed="true">                          <android.view.ViewGroup index="0" package="com.chewy.android" class="android.view.ViewGroup" text="" resource-id="com.chewy.android:id/item_autoship_banner" checkable="false" checked="false" clickable="true" enabled="true" focusable="true" focused="false" long-clickable="false" password="false" scrollable="false" selected="false" bounds="[0,529][1080,645]" displayed="true">                            <android.widget.TextView index="0" package="com.chewy.android" class="android.widget.TextView" text="Save 30% on your first " resource-id="com.chewy.android:id/highlightText" checkable="false" checked="false" clickable="false" enabled="true" focusable="false" focused="false" long-clickable="false" password="false" scrollable="false" selected="false" bounds="[33,551][1058,623]" displayed="true" />                          </android.view.ViewGroup>                          <android.view.ViewGroup index="1" package="com.chewy.android" class="android.view.ViewGroup" text="" checkable="false" checked="false" clickable="false" enabled="true" focusable="false" focused="false" long-clickable="false" password="false" scrollable="false" selected="false" bounds="[0,755][1080,887]" displayed="true">                            <android.widget.TextView index="0" package="com.chewy.android" class="android.widget.TextView" text="BROWSE" resource-id="com.chewy.android:id/leftText" checkable="false" checked="false" clickable="false" enabled="true" focusable="false" focused="false" long-clickable="false" password="false" scrollable="false" selected="false" bounds="[44,799][177,843]" displayed="true" />                            <android.widget.TextView index="1" package="com.chewy.android" class="android.widget.TextView" text="198 results" resource-id="com.chewy.android:id/rightText" checkable="false" checked="false" clickable="false" enabled="true" focusable="false" focused="false" long-clickable="false" password="false" scrollable="false" selected="false" bounds="[876,799][1036,843]" displayed="true" />                          </android.view.ViewGroup>                          <android.view.ViewGroup index="2" package="com.chewy.android" class="android.view.ViewGroup" text="" resource-id="com.chewy.android:id/item_browse_result" checkable="false" checked="false" clickable="true" enabled="true" focusable="true" focused="false" long-clickable="false" password="false" scrollable="false" selected="false" bounds="[0,887][1080,1427]" displayed="true">                            <android.widget.FrameLayout index="0" package="com.chewy.android" class="android.widget.FrameLayout" text="" resource-id="com.chewy.android:id/item_browse_result_product_image" checkable="false" checked="false" clickable="false" enabled="true" focusable="false" focused="false" long-clickable="false" password="false" scrollable="false" selected="false" bounds="[44,931][388,1275]" displayed="true">                              <android.widget.ImageView index="0" package="com.chewy.android" class="android.widget.ImageView" text="" resource-id="com.chewy.android:id/image" checkable="false" checked="false" clickable="false" enabled="true" focusable="false" focused="false" long-clickable="false" password="false" scrollable="false" selected="false" bounds="[44,931][388,1275]" displayed="true" />                            </android.widget.FrameLayout>                            <android.widget.FrameLayout index="1" package="com.chewy.android" class="android.widget.FrameLayout" text="" checkable="false" checked="false" clickable="false" enabled="true" focusable="false" focused="false" long-clickable="false" password="false" scrollable="false" selected="false" bounds="[278,887][432,1041]" displayed="true">                              <android.widget.ImageButton index="0" package="com.chewy.android" class="android.widget.ImageButton" text="" content-desc="Favorite" resource-id="com.chewy.android:id/favoritesButton" checkable="false" checked="false" clickable="true" enabled="true" focusable="true" focused="false" long-clickable="false" password="false" scrollable="false" selected="false" bounds="[300,909][410,1019]" displayed="true" />                            </android.widget.FrameLayout>                            <android.widget.TextView index="2" package="com.chewy.android" class="android.widget.TextView" text="Fancy Feast Grilled Seafood Feast Variety Pack Canned Cat Food, 3-oz, case of 24" resource-id="com.chewy.android:id/productTitleText" checkable="false" checked="false" clickable="false" enabled="true" focusable="false" focused="false" long-clickable="false" password="false" scrollable="false" selected="false" bounds="[432,931][1047,1128]" displayed="true" />                            <android.widget.TextView index="3" package="com.chewy.android" class="android.widget.TextView" text="$14.79" content-desc="Marked down to $14.79 from $16.79" resource-id="com.chewy.android:id/productSalePrice" checkable="false" checked="false" clickable="false" enabled="true" focusable="false" focused="false" long-clickable="false" password="false" scrollable="false" selected="false" bounds="[432,1150][592,1217]" displayed="true" />                            <android.widget.TextView index="4" package="com.chewy.android" class="android.widget.TextView" text="$16.79" resource-id="com.chewy.android:id/strikeThroughPrice" checkable="false" checked="false" clickable="false" enabled="true" focusable="false" focused="false" long-clickable="false" password="false" scrollable="false" selected="false" bounds="[614,1159][740,1215]" displayed="true" />                            <android.widget.TextView index="6" package="com.chewy.android" class="android.widget.TextView" text="More Choices Available" resource-id="com.chewy.android:id/moreChoicesText" checkable="false" checked="false" clickable="false" enabled="true" focusable="false" focused="false" long-clickable="false" password="false" scrollable="false" selected="false" bounds="[55,1297][366,1388]" displayed="true" />                            <android.widget.TextView index="7" package="com.chewy.android" class="android.widget.TextView" text="FREE 1-3 day shipping over $49" content-desc="FREE 1-3 day shipping over $49" resource-id="com.chewy.android:id/freeShippingText" checkable="false" checked="false" clickable="false" enabled="true" focusable="false" focused="false" long-clickable="false" password="false" scrollable="false" selected="false" bounds="[432,1261][1047,1305]" displayed="true" />                            <android.widget.LinearLayout index="8" package="com.chewy.android" class="android.widget.LinearLayout" text="" content-desc="4.6 out of 5 stars. 1048 reviews" resource-id="com.chewy.android:id/itemStarsRating" checkable="false" checked="false" clickable="false" enabled="true" focusable="false" focused="false" long-clickable="false" password="false" scrollable="false" selected="false" bounds="[432,1327][1047,1380]" displayed="true">                              <android.widget.RatingBar index="0" package="com.chewy.android" class="android.widget.RatingBar" text="4550.0" resource-id="com.chewy.android:id/ratingStars" checkable="false" checked="false" clickable="false" enabled="true" focusable="false" focused="false" long-clickable="false" password="false" scrollable="false" selected="false" bounds="[432,1331][652,1375]" displayed="true" />                              <android.widget.TextView index="1" package="com.chewy.android" class="android.widget.TextView" text="1048" resource-id="com.chewy.android:id/ratingQuantity" checkable="false" checked="false" clickable="false" enabled="true" focusable="false" focused="false" long-clickable="false" password="false" scrollable="false" selected="false" bounds="[663,1327][751,1380]" displayed="true" />                            </android.widget.LinearLayout>                            <android.view.View index="9" package="com.chewy.android" class="android.view.View" text="" resource-id="com.chewy.android:id/item_browse_result_product_divider" checkable="false" checked="false" clickable="false" enabled="true" focusable="false" focused="false" long-clickable="false" password="false" scrollable="false" selected="false" bounds="[432,1424][1080,1427]" displayed="true" />                          </android.view.ViewGroup>                          <android.view.ViewGroup index="3" package="com.chewy.android" class="android.view.ViewGroup" text="" resource-id="com.chewy.android:id/item_browse_result" checkable="false" checked="false" clickable="true" enabled="true" focusable="true" focused="false" long-clickable="false" password="false" scrollable="false" selected="false" bounds="[0,1427][1080,1977]" displayed="true">                            <android.widget.FrameLayout index="0" package="com.chewy.android" class="android.widget.FrameLayout" text="" resource-id="com.chewy.android:id/item_browse_result_product_image" checkable="false" checked="false" clickable="false" enabled="true" focusable="false" focused="false" long-clickable="false" password="false" scrollable="false" selected="false" bounds="[44,1471][388,1815]" displayed="true">                              <android.widget.ImageView index="0" package="com.chewy.android" class="android.widget.ImageView" text="" resource-id="com.chewy.android:id/image" checkable="false" checked="false" clickable="false" enabled="true" focusable="false" focused="false" long-clickable="false" password="false" scrollable="false" selected="false" bounds="[44,1471][388,1815]" displayed="true" />                            </android.widget.FrameLayout>                            <android.widget.FrameLayout index="1" package="com.chewy.android" class="android.widget.FrameLayout" text="" checkable="false" checked="false" clickable="false" enabled="true" focusable="false" focused="false" long-clickable="false" password="false" scrollable="false" selected="false" bounds="[278,1427][432,1581]" displayed="true">                              <android.widget.ImageButton index="0" package="com.chewy.android" class="android.widget.ImageButton" text="" content-desc="Favorite" resource-id="com.chewy.android:id/favoritesButton" checkable="false" checked="false" clickable="true" enabled="true" focusable="true" focused="false" long-clickable="false" password="false" scrollable="false" selected="false" bounds="[300,1449][410,1559]" displayed="true" />                            </android.widget.FrameLayout>                            <android.widget.TextView index="2" package="com.chewy.android" class="android.widget.TextView" text="Fancy Feast Gravy Lovers Poultry &amp; Beef Feast Variety Pack Canned Cat Food, 3-oz, case of 24" resource-id="com.chewy.android:id/productTitleText" checkable="false" checked="false" clickable="false" enabled="true" focusable="false" focused="false" long-clickable="false" password="false" scrollable="false" selected="false" bounds="[432,1471][1047,1737]" displayed="true" />                            <android.widget.TextView index="3" package="com.chewy.android" class="android.widget.TextView" text="$14.89" content-desc="Marked down to $14.89 from $16.79" resource-id="com.chewy.android:id/productSalePrice" checkable="false" checked="false" clickable="false" enabled="true" focusable="false" focused="false" long-clickable="false" password="false" scrollable="false" selected="false" bounds="[432,1759][592,1826]" displayed="true" />                            <android.widget.TextView index="4" package="com.chewy.android" class="android.widget.TextView" text="$16.79" resource-id="com.chewy.android:id/strikeThroughPrice" checkable="false" checked="false" clickable="false" enabled="true" focusable="false" focused="false" long-clickable="false" password="false" scrollable="false" selected="false" bounds="[614,1768][740,1824]" displayed="true" />                            <android.widget.TextView index="5" package="com.chewy.android" class="android.widget.TextView" text="More Choices Available" resource-id="com.chewy.android:id/moreChoicesText" checkable="false" checked="false" clickable="false" enabled="true" focusable="false" focused="false" long-clickable="false" password="false" scrollable="false" selected="false" bounds="[55,1837][366,1928]" displayed="true" />                            <android.widget.TextView index="7" package="com.chewy.android" class="android.widget.TextView" text="FREE 1-3 day shipping over $49" content-desc="FREE 1-3 day shipping over $49" resource-id="com.chewy.android:id/freeShippingText" checkable="false" checked="false" clickable="false" enabled="true" focusable="false" focused="false" long-clickable="false" password="false" scrollable="false" selected="false" bounds="[432,1870][1047,1914]" displayed="true" />                            <android.widget.LinearLayout index="8" package="com.chewy.android" class="android.widget.LinearLayout" text="" content-desc="4.5 out of 5 stars. 1493 reviews" resource-id="com.chewy.android:id/itemStarsRating" checkable="false" checked="false" clickable="false" enabled="true" focusable="false" focused="false" long-clickable="false" password="false" scrollable="false" selected="false" bounds="[432,1936][1047,1977]" displayed="true">                              <android.widget.RatingBar index="0" package="com.chewy.android" class="android.widget.RatingBar" text="4500.0" resource-id="com.chewy.android:id/ratingStars" checkable="false" checked="false" clickable="false" enabled="true" focusable="false" focused="false" long-clickable="false" password="false" scrollable="false" selected="false" bounds="[432,1940][652,1977]" displayed="true" />                              <android.widget.TextView index="1" package="com.chewy.android" class="android.widget.TextView" text="1493" resource-id="com.chewy.android:id/ratingQuantity" checkable="false" checked="false" clickable="false" enabled="true" focusable="false" focused="false" long-clickable="false" password="false" scrollable="false" selected="false" bounds="[663,1936][751,1977]" displayed="true" />                            </android.widget.LinearLayout>                            <android.view.View index="9" package="com.chewy.android" class="android.view.View" text="" resource-id="com.chewy.android:id/item_browse_result_product_divider" checkable="false" checked="false" clickable="false" enabled="true" focusable="false" focused="false" long-clickable="false" password="false" scrollable="false" selected="false" bounds="[432,2033][1080,2036]" displayed="true" />                          </android.view.ViewGroup>                          <android.view.ViewGroup index="4" package="com.chewy.android" class="android.view.ViewGroup" text="" resource-id="com.chewy.android:id/item_browse_result" checkable="false" checked="false" clickable="true" enabled="true" focusable="true" focused="false" long-clickable="false" password="false" scrollable="false" selected="false" bounds="[0,2036][1080,2148]" displayed="true">                            <android.widget.FrameLayout index="0" package="com.chewy.android" class="android.widget.FrameLayout" text="" resource-id="com.chewy.android:id/item_browse_result_product_image" checkable="false" checked="false" clickable="false" enabled="true" focusable="false" focused="false" long-clickable="false" password="false" scrollable="false" selected="false" bounds="[44,2080][388,2148]" displayed="true">                              <android.widget.ImageView index="0" package="com.chewy.android" class="android.widget.ImageView" text="" resource-id="com.chewy.android:id/image" checkable="false" checked="false" clickable="false" enabled="true" focusable="false" focused="false" long-clickable="false" password="false" scrollable="false" selected="false" bounds="[44,2080][388,2148]" displayed="true" />                            </android.widget.FrameLayout>                            <android.widget.FrameLayout index="1" package="com.chewy.android" class="android.widget.FrameLayout" text="" checkable="false" checked="false" clickable="false" enabled="true" focusable="false" focused="false" long-clickable="false" password="false" scrollable="false" selected="false" bounds="[278,2036][432,2148]" displayed="true">                              <android.widget.ImageButton index="0" package="com.chewy.android" class="android.widget.ImageButton" text="" content-desc="Favorite" resource-id="com.chewy.android:id/favoritesButton" checkable="false" checked="false" clickable="true" enabled="true" focusable="true" focused="false" long-clickable="false" password="false" scrollable="false" selected="false" bounds="[300,2058][410,2148]" displayed="true" />                            </android.widget.FrameLayout>                            <android.widget.TextView index="2" package="com.chewy.android" class="android.widget.TextView" text="Fancy Feast Classic Seafood Feast Variety Pack Canned Cat Food, 3-oz, case of 24" resource-id="com.chewy.android:id/productTitleText" checkable="false" checked="false" clickable="false" enabled="true" focusable="false" focused="false" long-clickable="false" password="false" scrollable="false" selected="false" bounds="[432,2080][1047,2148]" displayed="true" />                          </android.view.ViewGroup>                        </androidx.recyclerview.widget.RecyclerView>                        <android.widget.Button index="1" package="com.chewy.android" class="android.widget.Button" text="Filter" resource-id="com.chewy.android:id/sortFilterButton" checkable="false" checked="false" clickable="true" enabled="true" focusable="true" focused="false" long-clickable="false" password="false" scrollable="false" selected="false" bounds="[375,1950][705,1977]" displayed="true" />                      </android.view.ViewGroup>                    </android.view.ViewGroup>                  </android.widget.FrameLayout>                </android.view.ViewGroup>              </android.view.ViewGroup>            </androidx.drawerlayout.widget.DrawerLayout>          </android.widget.FrameLayout>        </android.widget.LinearLayout>      </android.widget.FrameLayout>    </android.widget.LinearLayout>    <android.view.View index="1" package="com.chewy.android" class="android.view.View" text="" resource-id="android:id/statusBarBackground" checkable="false" checked="false" clickable="false" enabled="true" focusable="false" focused="false" long-clickable="false" password="false" scrollable="false" selected="false" bounds="[0,0][1080,171]" displayed="true" />  </android.widget.FrameLayout></hierarchy>